alitiq/__init__.py
alitiq/base.py
alitiq/load_forecast.py
alitiq/solar_power_forecast.py
alitiq/wind_power_forecast.py
alitiq/enumerations/__init__.py
alitiq/enumerations/forecast_models.py
alitiq/enumerations/services.py
alitiq/models/__init__.py
alitiq/models/load_forecast.py
alitiq/models/solar_power_forecast.py
alitiq/models/wind_power_forecast.py
alitiq-2025.8.26.dist-info/LICENSE
alitiq-2025.8.26.dist-info/METADATA
alitiq-2025.8.26.dist-info/WHEEL
alitiq-2025.8.26.dist-info/top_level.txt
alitiq-2025.8.26.dist-info/zip-safe
alitiq-2025.8.26.dist-info/RECORD
