Metadata-Version: 2.1
Name: alitiq
Version: 2025.8.26
Summary: alitiq python SDK
Author: Daniel Lassahn | alitiq GmbH
Author-email: info@alitiq.com
License: IP belongs to alitiq GmbH
Keywords: energy,forecasting,solar,pv,demand,prediction,wind,windpower,solarpower,power,powerprediction
Classifier: Programming Language :: Python :: 3.12
Classifier: Operating System :: OS Independent
License-File: LICENSE
